scanux/__init__.py
scanux/cli.py
scanux/core/__init__.py
scanux/core/reporter.py
scanux/core/scanner.py
scanux/core/utils.py
scanux/modules/__init__.py
scanux/modules/network.py
scanux/modules/performance.py
scanux/modules/security.py
scanux/modules/system.py
scanux-1.1.29.dist-info/licenses/LICENSE
scanux-1.1.29.dist-info/METADATA
scanux-1.1.29.dist-info/WHEEL
scanux-1.1.29.dist-info/entry_points.txt
scanux-1.1.29.dist-info/top_level.txt
scanux-1.1.29.dist-info/RECORD
