Metadata-Version: 2.4
Name: scanux
Version: 1.1.29
Summary: System security and performance scanner
Author-email: Yassir aitelaizzi <yassir.aitelaizzi@gmail.com>
Project-URL: Homepage, https://github.com/yourusername/scanux
Project-URL: Issues, https://github.com/yourusername/scanux/issues
Classifier: Development Status :: 3 - Alpha
Classifier: Intended Audience :: System Administrators
Classifier: Programming Language :: Python :: 3
Classifier: License :: OSI Approved :: MIT License
Requires-Python: >=3.8
License-File: LICENSE
Requires-Dist: psutil>=5.9.0
Requires-Dist: python-nmap>=0.7.1
Requires-Dist: netifaces>=0.11.0
Requires-Dist: rich>=10.0.0
Requires-Dist: pyyaml>=6.0
Dynamic: license-file
